HISTORY.rst
LICENSE.txt
MANIFEST.in
README.rst
requirements.txt
setup.py
test_circonus.py
circonus/__init__.py
circonus/annotation.py
circonus/client.py
circonus/graph.py
circonus/metric.py
circonus/tag.py
circonus/util.py
circonus.egg-info/PKG-INFO
circonus.egg-info/SOURCES.txt
circonus.egg-info/dependency_links.txt
circonus.egg-info/requires.txt
circonus.egg-info/top_level.txt
circonus/collectd/__init__.py
circonus/collectd/cpu.py
circonus/collectd/df.py
circonus/collectd/graph.py
circonus/collectd/interface.py
circonus/collectd/memory.py