Metadata-Version: 1.1
Name: circonus
Version: 0.0.22
Summary: Interact with the Circonus REST API.
Home-page: https://github.com/monetate/circonus
Author: Monetate Inc.
Author-email: kmolendyke@monetate.com
License: MIT
Keywords: circonus monitoring analytics
Platform: UNKNOWN
Classifier: Development Status :: 3 - Alpha
Classifier: Intended Audience :: Developers
Classifier: License :: OSI Approved :: MIT License
Classifier: Programming Language :: Python :: 2.7
